rom.v
module rom (
  input clk, //clk
  input en, //enable
  input [3:0] addr, //address
  output reg [3:0] data //output data
);
  
  reg [3:0] mem [15:0]; //4 bit data and 16 locations
  
  always @ (posedge clk) 
    begin
      if (en)
        data <= mem[addr];
      else 
        data <= 4'bxxxx;
    end
  
  initial 
    begin    
      mem[0] = 4'b0010;
      mem[1] = 4'b0010;
      mem[2] = 4'b1110;
      mem[3] = 4'b0010;
      mem[4] = 4'b0100;
      mem[5] = 4'b1010;
      mem[6] = 4'b1100;
      mem[7] = 4'b0000;
      mem[8] = 4'b1010;
      mem[9] = 4'b0010;
      mem[10] = 4'b1110;
      mem[11] = 4'b0010;
      mem[12] = 4'b0100;
      mem[13] = 4'b1010;
      mem[14] = 4'b1100;
      mem[15] = 4'b0000;
    end    

endmodule

rom_tb.v
module rom_tb;
  reg clk; //clk
  reg en; //enable
  reg [3:0] addr; //address
  wire [3:0] data; //output data
  
  rom r1(
    .clk(clk),
    .en(en),
    .addr(addr),
    .data(data)
  );
  
  initial
    begin
      $dumpfile("dump.vcd");
      $dumpvars(1, rom_tb);       
      
      clk=1'b1;
    end

    always
    #5 clk = ~clk;
  
  initial
    begin
      en = 1'b0;
      #10;                  
      
      en = 1'b1;      
      addr = 4'b1010;
      #10;
      
      addr = 4'b0110;
      #10;
      
      addr = 4'b0011;
      #10;
      
      en = 1'b0;
      addr = 4'b1111;
      #10;
            
      en = 1'b1;
      addr = 4'b1000;
      #10;
      
      addr = 4'b0000;
      #10;
      
      addr = 4'bxxxx;
      #10;
    end
  
  initial
    begin
      #80 $finish;
    end
  
endmodule

dump.vcd
$date
	Wed Jul 16 21:40:46 2025
$end
$version
	Icarus Verilog
$end
$timescale
	1s
$end
$scope module rom_tb $end
$var wire 4 ! data [3:0] $end
$var reg 4 " addr [3:0] $end
$var reg 1 # clk $end
$var reg 1 $ en $end
$upscope $end
$enddefinitions $end
#0
$dumpvars
0$
1#
bx "
bx !
$end
#5
0#
#10
b1110 !
1#
b1010 "
1$
#15
0#
#20
b1100 !
1#
b110 "
#25
0#
#30
b10 !
1#
b11 "
#35
0#
#40
bx !
1#
b1111 "
0$
#45
0#
#50
b1010 !
1#
b1000 "
1$
#55
0#
#60
b10 !
1#
b0 "
#65
0#
#70
bx !
1#
bx "
